Metadata-Version: 2.1
Name: ximreader
Version: 1.0.0
Summary: Python extension for reading xim files
Author: Dinesh Kumar
Author-email: Dinesh Kumar <dkumar@lbl.gov>
Project-URL: Homepage, https://github.com/aryabhatt/ximreader
Project-URL: Issues, https://github.com/aryabhatt/ximreader/issues
Classifier: Programming Language :: Python :: 3
Classifier: Operating System :: OS Independent
Requires-Python: >=3.8
License-File: LICENSE
Requires-Dist: numpy
